README.md
setup.py
code_engine/__init__.py
code_engine/app.py
code_engine.egg-info/PKG-INFO
code_engine.egg-info/SOURCES.txt
code_engine.egg-info/dependency_links.txt
code_engine.egg-info/requires.txt
code_engine.egg-info/top_level.txt
code_engine/util/__init__.py
code_engine/util/debug.py
code_engine/util/filehelper.py