Metadata-Version: 1.1
Name: code-engine
Version: 1.0.13
Summary: Code-engine is a dead simple engine based on Jinja2 to make you free from generation process.
Home-page: https://github.com/cao5zy/code-engine
Author: Zongying Cao
Author-email: zongying.cao@dxc.com
License: Apache
Platform: UNKNOWN
Classifier: Development Status :: 4 - Beta
Classifier: Intended Audience :: Developers
Classifier: License :: OSI Approved :: Apache Software License
Classifier: Natural Language :: English
Classifier: Operating System :: OS Independent
Classifier: Programming Language :: Python :: 3
Classifier: Topic :: Software Development :: Libraries
